{
  "updatedAt": "2026-07-20T21:38:57.949Z",
  "source": "kis+yahoo",
  "action": "volume",
  "count": 50,
  "stocks": [
    {
      "rank": 1,
      "ticker": "MU",
      "name": "마이크론 테크놀로지",
      "price": 871.5,
      "changePct": 2.66,
      "changePoints": 22.58,
      "volume": 27762903,
      "marketCap": 977444601856,
      "tradingValue": 24414003926,
      "exchange": "NAS"
    },
    {
      "rank": 2,
      "ticker": "NVDA",
      "name": "엔비디아",
      "price": 202.68,
      "changePct": -0.06,
      "changePoints": -0.12,
      "volume": 65604754,
      "marketCap": 4923644706816,
      "tradingValue": 13439729196,
      "exchange": "NAS"
    },
    {
      "rank": 3,
      "ticker": "AAPL",
      "name": "애플",
      "price": 326.7,
      "changePct": -2.11,
      "changePoints": -7.04,
      "volume": 38225437,
      "marketCap": 4796743417856,
      "tradingValue": 12522485839,
      "exchange": "NAS"
    },
    {
      "rank": 4,
      "ticker": "QQQ",
      "name": "INVESCO QQQ TRUST",
      "price": 696.05,
      "changePct": 0.1,
      "changePoints": 0.7,
      "volume": 17838738,
      "marketCap": 273617255000,
      "tradingValue": 12486757783,
      "exchange": "NAS"
    },
    {
      "rank": 5,
      "ticker": "SNDK",
      "name": "샌디스크",
      "price": 1404.5,
      "changePct": 3.67,
      "changePoints": 49.72,
      "volume": 8552259,
      "marketCap": 205985447936,
      "tradingValue": 12091360910,
      "exchange": "NAS"
    },
    {
      "rank": 6,
      "ticker": "TSLA",
      "name": "테슬라",
      "price": 370.26,
      "changePct": -2.78,
      "changePoints": -10.59,
      "volume": 24838255,
      "marketCap": 1388002803712,
      "tradingValue": 9285852691,
      "exchange": "NAS"
    },
    {
      "rank": 7,
      "ticker": "AMD",
      "name": "AMD",
      "price": 504.1,
      "changePct": 1.68,
      "changePoints": 8.33,
      "volume": 17838635,
      "marketCap": 821121515520,
      "tradingValue": 9128867089,
      "exchange": "NAS"
    },
    {
      "rank": 8,
      "ticker": "MSFT",
      "name": "마이크로소프트",
      "price": 401.3,
      "changePct": 1.9,
      "changePoints": 7.48,
      "volume": 20085613,
      "marketCap": 2988385239040,
      "tradingValue": 8060356497,
      "exchange": "NAS"
    },
    {
      "rank": 9,
      "ticker": "GOOGL",
      "name": "알파벳 A",
      "price": 352.6,
      "changePct": 1.68,
      "changePoints": 5.83,
      "volume": 18521685,
      "marketCap": 2053542400000,
      "tradingValue": 6573478863,
      "exchange": "NAS"
    },
    {
      "rank": 10,
      "ticker": "INTC",
      "name": "인텔",
      "price": 97.15,
      "changePct": 2.22,
      "changePoints": 2.11,
      "volume": 64088989,
      "marketCap": 487823540224,
      "tradingValue": 6299042570,
      "exchange": "NAS"
    },
    {
      "rank": 11,
      "ticker": "AMZN",
      "name": "아마존닷컴",
      "price": 249.96,
      "changePct": 1.1,
      "changePoints": 2.72,
      "volume": 24264577,
      "marketCap": 2689169883136,
      "tradingValue": 6071583204,
      "exchange": "NAS"
    },
    {
      "rank": 12,
      "ticker": "SPCX",
      "name": "스페이스X",
      "price": 120.39,
      "changePct": -2.9,
      "changePoints": -3.6,
      "volume": 42727440,
      "marketCap": 1578446666653,
      "tradingValue": 5210532634,
      "exchange": "NAS"
    },
    {
      "rank": 13,
      "ticker": "META",
      "name": "메타 플랫폼스(페이스북)",
      "price": 645.36,
      "changePct": -0.1,
      "changePoints": -0.65,
      "volume": 7342801,
      "marketCap": 1639440580608,
      "tradingValue": 4786273369,
      "exchange": "NAS"
    },
    {
      "rank": 14,
      "ticker": "AVGO",
      "name": "브로드컴",
      "price": 378.62,
      "changePct": 2.1,
      "changePoints": 7.79,
      "volume": 11268031,
      "marketCap": 1799126515712,
      "tradingValue": 4272282351,
      "exchange": "NAS"
    },
    {
      "rank": 15,
      "ticker": "SKHY",
      "name": "SK하이닉스(ADR)",
      "price": 152.01,
      "changePct": -1.31,
      "changePoints": -2.02,
      "volume": 25037776,
      "marketCap": 1073016668160,
      "tradingValue": 3924207889,
      "exchange": "NAS"
    },
    {
      "rank": 16,
      "ticker": "MRVL",
      "name": "마벨 테크놀로지 그룹",
      "price": 195,
      "changePct": 3.35,
      "changePoints": 6.32,
      "volume": 18581810,
      "marketCap": 174967324672,
      "tradingValue": 3683269281,
      "exchange": "NAS"
    },
    {
      "rank": 17,
      "ticker": "GOOG",
      "name": "알파벳 C",
      "price": 352.23,
      "changePct": 1.77,
      "changePoints": 6.13,
      "volume": 9781224,
      "marketCap": 1921766880000,
      "tradingValue": 3459774207,
      "exchange": "NAS"
    },
    {
      "rank": 18,
      "ticker": "STX",
      "name": "시게이트 테크놀로지 홀딩스",
      "price": 804.61,
      "changePct": 2.15,
      "changePoints": 16.94,
      "volume": 4026982,
      "marketCap": 179932561408,
      "tradingValue": 3261152962,
      "exchange": "NAS"
    },
    {
      "rank": 19,
      "ticker": "PLTR",
      "name": "팔란티어 테크",
      "price": 134.5,
      "changePct": 1.6,
      "changePoints": 2.12,
      "volume": 22856734,
      "marketCap": 323277553664,
      "tradingValue": 3075879016,
      "exchange": "NAS"
    },
    {
      "rank": 20,
      "ticker": "NFLX",
      "name": "넷플릭스",
      "price": 67.58,
      "changePct": -1.99,
      "changePoints": -1.37,
      "volume": 42258332,
      "marketCap": 284649979904,
      "tradingValue": 2856426834,
      "exchange": "NAS"
    },
    {
      "rank": 21,
      "ticker": "AMAT",
      "name": "어플라이드 머티어리얼즈",
      "price": 524.72,
      "changePct": -0.93,
      "changePoints": -4.93,
      "volume": 4960527,
      "marketCap": 417384464384,
      "tradingValue": 2637336420,
      "exchange": "NAS"
    },
    {
      "rank": 22,
      "ticker": "IREN",
      "name": "IREN",
      "price": 40.67,
      "changePct": 20.97,
      "changePoints": 7.05,
      "volume": 64628028,
      "marketCap": 14366623744,
      "tradingValue": 2628421899,
      "exchange": "NAS"
    },
    {
      "rank": 23,
      "ticker": "ORCL",
      "name": "오라클",
      "price": 121.55,
      "changePct": -3.84,
      "changePoints": -4.85,
      "volume": 21131145,
      "marketCap": 349631578112,
      "tradingValue": 2585404038,
      "exchange": "NYS"
    },
    {
      "rank": 24,
      "ticker": "SMH",
      "name": "VANECK SEMICONDUCTOR",
      "price": 557.9,
      "changePct": 0.25,
      "changePoints": 1.39,
      "volume": 4145984,
      "marketCap": 6511195110,
      "tradingValue": 2338116774,
      "exchange": "NAS"
    },
    {
      "rank": 25,
      "ticker": "AAL",
      "name": "아메리칸 에어라인스 그룹",
      "price": 15.12,
      "changePct": 0.93,
      "changePoints": 0.14,
      "volume": 150865546,
      "marketCap": 10013371392,
      "tradingValue": 2288055459,
      "exchange": "NAS"
    },
    {
      "rank": 26,
      "ticker": "LITE",
      "name": "루멘텀 홀딩스",
      "price": 769.74,
      "changePct": 5.04,
      "changePoints": 36.93,
      "volume": 2914563,
      "marketCap": 59559788544,
      "tradingValue": 2277902184,
      "exchange": "NAS"
    },
    {
      "rank": 27,
      "ticker": "TQQQ",
      "name": "PROSHARES QQQ 3X",
      "price": 67.65,
      "changePct": 0.18,
      "changePoints": 0.12,
      "volume": 32896942,
      "marketCap": null,
      "tradingValue": 2269387369,
      "exchange": "NAS"
    },
    {
      "rank": 28,
      "ticker": "TSM",
      "name": "TSMC(ADR)",
      "price": 403.25,
      "changePct": 1.22,
      "changePoints": 4.86,
      "volume": 5472009,
      "marketCap": 2086518390784,
      "tradingValue": 2212015254,
      "exchange": "NYS"
    },
    {
      "rank": 29,
      "ticker": "NBIS",
      "name": "네비우스 그룹",
      "price": 191.4,
      "changePct": 7.7,
      "changePoints": 13.68,
      "volume": 11458155,
      "marketCap": 46366887936,
      "tradingValue": 2193090867,
      "exchange": "NAS"
    },
    {
      "rank": 30,
      "ticker": "SOXX",
      "name": "ISHARES SEMICONDUCTOR",
      "price": 523.44,
      "changePct": 0.31,
      "changePoints": 1.62,
      "volume": 4097982,
      "marketCap": 4004316000,
      "tradingValue": 2173194120,
      "exchange": "NAS"
    },
    {
      "rank": 31,
      "ticker": "WDC",
      "name": "웨스턴 디지털",
      "price": 488.26,
      "changePct": 2.31,
      "changePoints": 11.02,
      "volume": 4027284,
      "marketCap": 168004976640,
      "tradingValue": 1993513379,
      "exchange": "NAS"
    },
    {
      "rank": 32,
      "ticker": "ASML",
      "name": "ASML 홀딩(ADR)",
      "price": 1738.68,
      "changePct": -0.51,
      "changePoints": -8.91,
      "volume": 1124848,
      "marketCap": 667957592064,
      "tradingValue": 1968592499,
      "exchange": "NAS"
    },
    {
      "rank": 33,
      "ticker": "BE",
      "name": "블룸 에너지",
      "price": 198.74,
      "changePct": -7.55,
      "changePoints": -16.23,
      "volume": 9489251,
      "marketCap": 56052510720,
      "tradingValue": 1920336262,
      "exchange": "NYS"
    },
    {
      "rank": 34,
      "ticker": "APP",
      "name": "앱러빈",
      "price": 423.2,
      "changePct": -0.32,
      "changePoints": -1.36,
      "volume": 4459859,
      "marketCap": 142639923200,
      "tradingValue": 1911675627,
      "exchange": "NAS"
    },
    {
      "rank": 35,
      "ticker": "NU",
      "name": "누 홀딩스",
      "price": 13.99,
      "changePct": 2.94,
      "changePoints": 0.4,
      "volume": 135684880,
      "marketCap": 67578478592,
      "tradingValue": 1902179407,
      "exchange": "NYS"
    },
    {
      "rank": 36,
      "ticker": "LRCX",
      "name": "램 리서치",
      "price": 305.65,
      "changePct": -2.44,
      "changePoints": -7.64,
      "volume": 5983731,
      "marketCap": 383625166848,
      "tradingValue": 1855929083,
      "exchange": "NAS"
    },
    {
      "rank": 37,
      "ticker": "PATH",
      "name": "유아이패스",
      "price": 12.19,
      "changePct": 0.33,
      "changePoints": 0.04,
      "volume": 149476921,
      "marketCap": 6300342272,
      "tradingValue": 1844709566,
      "exchange": "NYS"
    },
    {
      "rank": 38,
      "ticker": "GEV",
      "name": "GE베르노바",
      "price": 1082,
      "changePct": 2.28,
      "changePoints": 24.12,
      "volume": 1566592,
      "marketCap": 289997258752,
      "tradingValue": 1695052544,
      "exchange": "NYS"
    },
    {
      "rank": 39,
      "ticker": "LLY",
      "name": "일라이 릴리",
      "price": 1144.8,
      "changePct": -2.91,
      "changePoints": -34.31,
      "volume": 1393581,
      "marketCap": 1022738235392,
      "tradingValue": 1614844128,
      "exchange": "NYS"
    },
    {
      "rank": 40,
      "ticker": "PANW",
      "name": "팰로 앨토 네트웍스",
      "price": 348.75,
      "changePct": -2.77,
      "changePoints": -9.94,
      "volume": 4012449,
      "marketCap": 284157902848,
      "tradingValue": 1426768218,
      "exchange": "NAS"
    },
    {
      "rank": 41,
      "ticker": "WMT",
      "name": "월마트",
      "price": 112.33,
      "changePct": -1.67,
      "changePoints": -1.91,
      "volume": 12615092,
      "marketCap": 892896411648,
      "tradingValue": 1420697484,
      "exchange": "NAS"
    },
    {
      "rank": 42,
      "ticker": "T",
      "name": "AT&T",
      "price": 21.99,
      "changePct": 0.8,
      "changePoints": 0.17,
      "volume": 64181147,
      "marketCap": 152516034560,
      "tradingValue": 1411343423,
      "exchange": "NYS"
    },
    {
      "rank": 43,
      "ticker": "HOOD",
      "name": "로빈훗 마케츠",
      "price": 99.24,
      "changePct": -0.72,
      "changePoints": -0.72,
      "volume": 14050418,
      "marketCap": 89402146816,
      "tradingValue": 1408309382,
      "exchange": "NAS"
    },
    {
      "rank": 44,
      "ticker": "SGOV",
      "name": "ISHARES 0-3M TREASURY BOND",
      "price": 100.58,
      "changePct": 0,
      "changePoints": 0,
      "volume": 13941196,
      "marketCap": null,
      "tradingValue": 1402277558,
      "exchange": "NYS"
    },
    {
      "rank": 45,
      "ticker": "ISRG",
      "name": "인튜이티브 서지컬",
      "price": 353.5,
      "changePct": 2.34,
      "changePoints": 8.08,
      "volume": 3944865,
      "marketCap": 125079699456,
      "tradingValue": 1394509778,
      "exchange": "NAS"
    },
    {
      "rank": 46,
      "ticker": "TLT",
      "name": "ISHARES 20+Y TREASURY BOND",
      "price": 83.93,
      "changePct": -0.7,
      "changePoints": -0.59,
      "volume": 16387988,
      "marketCap": 9207121000,
      "tradingValue": 1376313738,
      "exchange": "NAS"
    },
    {
      "rank": 47,
      "ticker": "KLAC",
      "name": "KLA",
      "price": 207,
      "changePct": -2.7,
      "changePoints": -5.74,
      "volume": 6460215,
      "marketCap": 271182741504,
      "tradingValue": 1356078017,
      "exchange": "NAS"
    },
    {
      "rank": 48,
      "ticker": "CSCO",
      "name": "시스코 시스템즈",
      "price": 110.51,
      "changePct": -1.28,
      "changePoints": -1.43,
      "volume": 12055337,
      "marketCap": 436316798976,
      "tradingValue": 1343587940,
      "exchange": "NAS"
    },
    {
      "rank": 49,
      "ticker": "CRWV",
      "name": "코어위브",
      "price": 73.52,
      "changePct": 0.42,
      "changePoints": 0.31,
      "volume": 16953799,
      "marketCap": 39859367936,
      "tradingValue": 1279680216,
      "exchange": "NAS"
    },
    {
      "rank": 50,
      "ticker": "CRM",
      "name": "세일스포스",
      "price": 173.46,
      "changePct": 1.57,
      "changePoints": 2.68,
      "volume": 7369453,
      "marketCap": 142334001152,
      "tradingValue": 1278305317,
      "exchange": "NYS"
    }
  ]
}
