{
  "updatedAt": "2026-07-16T08:38:59.523Z",
  "source": "kis+yahoo",
  "action": "market-cap",
  "count": 50,
  "stocks": [
    {
      "rank": 1,
      "ticker": "NVDA",
      "name": "엔비디아",
      "price": 209.81,
      "changePct": -1.27,
      "changePoints": -2.69,
      "volume": 124797151,
      "marketCap": 5146962558976,
      "tradingValue": 26276844619,
      "exchange": "NAS"
    },
    {
      "rank": 2,
      "ticker": "AAPL",
      "name": "애플",
      "price": 329.29,
      "changePct": 0.55,
      "changePoints": 1.79,
      "volume": 60957644,
      "marketCap": 4810109091840,
      "tradingValue": 20072742593,
      "exchange": "NAS"
    },
    {
      "rank": 3,
      "ticker": "MSFT",
      "name": "마이크로소프트",
      "price": 399.28,
      "changePct": 0.9,
      "changePoints": 3.65,
      "volume": 36253745,
      "marketCap": 2938911850496,
      "tradingValue": 14475395304,
      "exchange": "NAS"
    },
    {
      "rank": 4,
      "ticker": "AMZN",
      "name": "아마존닷컴",
      "price": 256.9,
      "changePct": 0.82,
      "changePoints": 1.94,
      "volume": 45240622,
      "marketCap": 2742632841216,
      "tradingValue": 11622315792,
      "exchange": "NAS"
    },
    {
      "rank": 5,
      "ticker": "GOOGL",
      "name": "알파벳 A",
      "price": 376.84,
      "changePct": 1.6,
      "changePoints": 5.92,
      "volume": 28284564,
      "marketCap": 2194716160000,
      "tradingValue": 10658755098,
      "exchange": "NAS"
    },
    {
      "rank": 6,
      "ticker": "TSM",
      "name": "TSMC(ADR)",
      "price": 405.23,
      "changePct": -3.4,
      "changePoints": -14.26,
      "volume": 258198,
      "marketCap": 2175622184960,
      "tradingValue": 104629576,
      "exchange": "NYS"
    },
    {
      "rank": 7,
      "ticker": "GOOG",
      "name": "알파벳 C",
      "price": 375.6,
      "changePct": 1.46,
      "changePoints": 5.39,
      "volume": 20258166,
      "marketCap": 2049273600000,
      "tradingValue": 7608967150,
      "exchange": "NAS"
    },
    {
      "rank": 8,
      "ticker": "AVGO",
      "name": "브로드컴",
      "price": 389.5,
      "changePct": -1.21,
      "changePoints": -4.78,
      "volume": 16324127,
      "marketCap": 1875818708992,
      "tradingValue": 6414086164,
      "exchange": "NAS"
    },
    {
      "rank": 9,
      "ticker": "SPCX",
      "name": "스페이스X",
      "price": 135.39,
      "changePct": 0.09,
      "changePoints": 0.12,
      "volume": 58040919,
      "marketCap": 1775113333318,
      "tradingValue": 7862099004,
      "exchange": "NAS"
    },
    {
      "rank": 10,
      "ticker": "META",
      "name": "메타 플랫폼스(페이스북)",
      "price": 682.88,
      "changePct": 0,
      "changePoints": 661.59,
      "volume": 25878,
      "marketCap": 1729453228032,
      "tradingValue": 17671569,
      "exchange": "NYS"
    },
    {
      "rank": 11,
      "ticker": "TSLA",
      "name": "테슬라",
      "price": 394.49,
      "changePct": 0.01,
      "changePoints": 0.04,
      "volume": 42956,
      "marketCap": 1481482829824,
      "tradingValue": 16945712,
      "exchange": "NAS"
    },
    {
      "rank": 12,
      "ticker": "SKHY",
      "name": "SK하이닉스(ADR)",
      "price": 166.07,
      "changePct": -5.89,
      "changePoints": -10.39,
      "volume": 330215,
      "marketCap": 1252610015232,
      "tradingValue": 54838805,
      "exchange": "NAS"
    },
    {
      "rank": 13,
      "ticker": "LLY",
      "name": "일라이 릴리",
      "price": 1157.83,
      "changePct": 0.1,
      "changePoints": 1.2,
      "volume": 2552230,
      "marketCap": 1031414808576,
      "tradingValue": 2955048461,
      "exchange": "NYS"
    },
    {
      "rank": 14,
      "ticker": "MU",
      "name": "마이크론 테크놀로지",
      "price": 883.5,
      "changePct": -2.3,
      "changePoints": -20.8,
      "volume": 229417,
      "marketCap": 1021287661568,
      "tradingValue": 202689920,
      "exchange": "NAS"
    },
    {
      "rank": 15,
      "ticker": "JPM",
      "name": "제이피모간 체이스",
      "price": 348.48,
      "changePct": 0.45,
      "changePoints": 1.57,
      "volume": 10749985,
      "marketCap": 922156204032,
      "tradingValue": 3746154773,
      "exchange": "NYS"
    },
    {
      "rank": 16,
      "ticker": "WMT",
      "name": "월마트",
      "price": 112.94,
      "changePct": 0.36,
      "changePoints": 0.41,
      "volume": 16467942,
      "marketCap": 895522635776,
      "tradingValue": 1865571345,
      "exchange": "NAS"
    },
    {
      "rank": 17,
      "ticker": "AMD",
      "name": "AMD",
      "price": 515,
      "changePct": -2.67,
      "changePoints": -14.14,
      "volume": 27826203,
      "marketCap": 862816043008,
      "tradingValue": 14709086586,
      "exchange": "NAS"
    },
    {
      "rank": 18,
      "ticker": "ASML",
      "name": "ASML 홀딩(ADR)",
      "price": 1786.51,
      "changePct": -1.58,
      "changePoints": -28.76,
      "volume": 4189308,
      "marketCap": 697245237248,
      "tradingValue": 7497227338,
      "exchange": "NAS"
    },
    {
      "rank": 19,
      "ticker": "BRK/B",
      "name": "버크셔 해서웨이 B",
      "price": 489.05,
      "changePct": 0.14,
      "changePoints": 0.68,
      "volume": 1979,
      "marketCap": 683837492767,
      "tradingValue": 967830,
      "exchange": "NYS"
    },
    {
      "rank": 20,
      "ticker": "V",
      "name": "비자",
      "price": 354.84,
      "changePct": -0.08,
      "changePoints": -0.28,
      "volume": 179,
      "marketCap": 675385311232,
      "tradingValue": 63516,
      "exchange": "NYS"
    },
    {
      "rank": 21,
      "ticker": "XOM",
      "name": "엑슨 모빌",
      "price": 144.19,
      "changePct": -0.22,
      "changePoints": -0.32,
      "volume": 1443,
      "marketCap": 598986326016,
      "tradingValue": 208066,
      "exchange": "NYS"
    },
    {
      "rank": 22,
      "ticker": "JNJ",
      "name": "존슨 앤드 존슨",
      "price": 248.52,
      "changePct": 0.61,
      "changePoints": 1.51,
      "volume": 567,
      "marketCap": 594630737920,
      "tradingValue": 140911,
      "exchange": "NYS"
    },
    {
      "rank": 23,
      "ticker": "INTC",
      "name": "인텔",
      "price": 101.05,
      "changePct": -1.88,
      "changePoints": -1.94,
      "volume": 120625478,
      "marketCap": 517627707392,
      "tradingValue": 12415169811,
      "exchange": "NAS"
    },
    {
      "rank": 24,
      "ticker": "QQQ",
      "name": "INVESCO QQQ TRUST",
      "price": 714.67,
      "changePct": -0.43,
      "changePoints": -3.09,
      "volume": 71998,
      "marketCap": 474969682000,
      "tradingValue": 51454811,
      "exchange": "NAS"
    },
    {
      "rank": 25,
      "ticker": "MA",
      "name": "마스타카드",
      "price": 539.52,
      "changePct": 0.8,
      "changePoints": 4.28,
      "volume": 312,
      "marketCap": 472902959104,
      "tradingValue": 168330,
      "exchange": "NYS"
    },
    {
      "rank": 26,
      "ticker": "AMAT",
      "name": "어플라이드 머티어리얼즈",
      "price": 571.5,
      "changePct": -1.37,
      "changePoints": -7.94,
      "volume": 25010,
      "marketCap": 460043911168,
      "tradingValue": 14293215,
      "exchange": "NAS"
    },
    {
      "rank": 27,
      "ticker": "CSCO",
      "name": "시스코 시스템즈",
      "price": 111.2,
      "changePct": -0.51,
      "changePoints": -0.57,
      "volume": 23829085,
      "marketCap": 440534138880,
      "tradingValue": 2671304827,
      "exchange": "NAS"
    },
    {
      "rank": 28,
      "ticker": "BAC",
      "name": "뱅크오브아메리카",
      "price": 61.61,
      "changePct": 0.03,
      "changePoints": 0.02,
      "volume": 43361012,
      "marketCap": 432236625920,
      "tradingValue": 2671471949,
      "exchange": "NYS"
    },
    {
      "rank": 29,
      "ticker": "ABBV",
      "name": "애브비",
      "price": 244.82,
      "changePct": 0.29,
      "changePoints": 0.71,
      "volume": 6388965,
      "marketCap": 431291793408,
      "tradingValue": 1565906326,
      "exchange": "NYS"
    },
    {
      "rank": 30,
      "ticker": "CAT",
      "name": "캐터필러",
      "price": 902.62,
      "changePct": -1.28,
      "changePoints": -11.68,
      "volume": 2703645,
      "marketCap": 421119229952,
      "tradingValue": 2460427129,
      "exchange": "NYS"
    },
    {
      "rank": 31,
      "ticker": "LRCX",
      "name": "램 리서치",
      "price": 330,
      "changePct": -1.62,
      "changePoints": -5.43,
      "volume": 10257338,
      "marketCap": 419479027712,
      "tradingValue": 3417855402,
      "exchange": "NAS"
    },
    {
      "rank": 32,
      "ticker": "COST",
      "name": "코스트코 홀세일",
      "price": 918.94,
      "changePct": 0.26,
      "changePoints": 2.38,
      "volume": 177,
      "marketCap": 406466068480,
      "tradingValue": 162652,
      "exchange": "NAS"
    },
    {
      "rank": 33,
      "ticker": "ORCL",
      "name": "오라클",
      "price": 133,
      "changePct": 0.38,
      "changePoints": 0.5,
      "volume": 54597,
      "marketCap": 381633626112,
      "tradingValue": 7261401,
      "exchange": "NYS"
    },
    {
      "rank": 34,
      "ticker": "UNH",
      "name": "유나이티드헬스 그룹",
      "price": 417.78,
      "changePct": -0.18,
      "changePoints": -0.74,
      "volume": 6764791,
      "marketCap": 380076589056,
      "tradingValue": 2836886510,
      "exchange": "NYS"
    },
    {
      "rank": 35,
      "ticker": "GE",
      "name": "GE에어로스페이스",
      "price": 358.88,
      "changePct": -0.41,
      "changePoints": -1.48,
      "volume": 386,
      "marketCap": 376504352768,
      "tradingValue": 138528,
      "exchange": "NYS"
    },
    {
      "rank": 36,
      "ticker": "BRK/A",
      "name": "버크셔 해서웨이 A",
      "price": 733180,
      "changePct": 0,
      "changePoints": 0,
      "volume": 172,
      "marketCap": 370766926460,
      "tradingValue": 126271258,
      "exchange": "NYS"
    },
    {
      "rank": 37,
      "ticker": "CVX",
      "name": "셰브론",
      "price": 181.18,
      "changePct": -0.23,
      "changePoints": -0.42,
      "volume": 6665707,
      "marketCap": 361674145792,
      "tradingValue": 1207692794,
      "exchange": "NYS"
    },
    {
      "rank": 38,
      "ticker": "MS",
      "name": "모간스탠리",
      "price": 228,
      "changePct": -0.24,
      "changePoints": -0.55,
      "volume": 1298,
      "marketCap": 359280607232,
      "tradingValue": 295944,
      "exchange": "NYS"
    },
    {
      "rank": 39,
      "ticker": "KO",
      "name": "코카콜라",
      "price": 82.99,
      "changePct": 0.65,
      "changePoints": 0.54,
      "volume": 18383759,
      "marketCap": 354739650560,
      "tradingValue": 1525668159,
      "exchange": "NYS"
    },
    {
      "rank": 40,
      "ticker": "PG",
      "name": "프록터 앤드 갬블",
      "price": 149.73,
      "changePct": 1.13,
      "changePoints": 1.67,
      "volume": 33,
      "marketCap": 344749080576,
      "tradingValue": 4941,
      "exchange": "NYS"
    },
    {
      "rank": 41,
      "ticker": "HSBC",
      "name": "HSBC 홀딩스(ADR)",
      "price": 100.51,
      "changePct": 0.05,
      "changePoints": 0.05,
      "volume": 2655,
      "marketCap": 344541822976,
      "tradingValue": 266854,
      "exchange": "NYS"
    },
    {
      "rank": 42,
      "ticker": "HD",
      "name": "홈 디포",
      "price": 342.32,
      "changePct": 0.26,
      "changePoints": 0.89,
      "volume": 29,
      "marketCap": 340455522304,
      "tradingValue": 9927,
      "exchange": "NYS"
    },
    {
      "rank": 43,
      "ticker": "GS",
      "name": "골드만삭스",
      "price": 1148.48,
      "changePct": -0.31,
      "changePoints": -3.59,
      "volume": 2735516,
      "marketCap": 339869171712,
      "tradingValue": 3141685416,
      "exchange": "NYS"
    },
    {
      "rank": 44,
      "ticker": "PLTR",
      "name": "팔란티어 테크",
      "price": 134.93,
      "changePct": 0.87,
      "changePoints": 1.16,
      "volume": 44074,
      "marketCap": 320664436736,
      "tradingValue": 5946905,
      "exchange": "NAS"
    },
    {
      "rank": 45,
      "ticker": "NFLX",
      "name": "넷플릭스",
      "price": 74.15,
      "changePct": 0.64,
      "changePoints": 0.47,
      "volume": 59620,
      "marketCap": 310251651072,
      "tradingValue": 4420823,
      "exchange": "NAS"
    },
    {
      "rank": 46,
      "ticker": "MRK",
      "name": "머크",
      "price": 123.61,
      "changePct": 0,
      "changePoints": 0,
      "volume": 9053781,
      "marketCap": 305294999552,
      "tradingValue": 1119137869,
      "exchange": "NYS"
    },
    {
      "rank": 47,
      "ticker": "RY",
      "name": "로열 뱅크 오브 캐나다",
      "price": 222.42,
      "changePct": 2.09,
      "changePoints": 4.55,
      "volume": 1530919,
      "marketCap": 302765735936,
      "tradingValue": 340507004,
      "exchange": "NYS"
    },
    {
      "rank": 48,
      "ticker": "KLAC",
      "name": "KLA",
      "price": 221.5,
      "changePct": -1.34,
      "changePoints": -3,
      "volume": 10625456,
      "marketCap": 293258788864,
      "tradingValue": 2373987150,
      "exchange": "NAS"
    },
    {
      "rank": 49,
      "ticker": "PANW",
      "name": "팰로 앨토 네트웍스",
      "price": 353.24,
      "changePct": -0.22,
      "changePoints": -0.78,
      "volume": 6703793,
      "marketCap": 288526303232,
      "tradingValue": 2385611989,
      "exchange": "NAS"
    },
    {
      "rank": 50,
      "ticker": "BABA",
      "name": "알리바바 그룹 홀딩(ADR)",
      "price": 119.6,
      "changePct": 1.62,
      "changePoints": 1.91,
      "volume": 20233332,
      "marketCap": 282087882752,
      "tradingValue": 2419906507,
      "exchange": "NYS"
    }
  ]
}
